liga/easyocr/__init__.py
liga/easyocr/codegen.py
liga/easyocr/models/__init__.py
liga/easyocr/models/ch_sim.py
liga/easyocr/models/ocr.py
liga_easyocr-0.2.0.dist-info/METADATA
liga_easyocr-0.2.0.dist-info/WHEEL
liga_easyocr-0.2.0.dist-info/namespace_packages.txt
liga_easyocr-0.2.0.dist-info/top_level.txt
liga_easyocr-0.2.0.dist-info/RECORD
