Metadata-Version: 2.1
Name: liga-easyocr
Version: 0.2.0
Requires-Python: <3.10,>=3.8
Requires-Dist: easyocr
Requires-Dist: ligavision
